CHANGELOG.txt
LICENSE.txt
MANIFEST.in
README.md
setup.py
midas_engine/__init__.py
midas_engine.egg-info/PKG-INFO
midas_engine.egg-info/SOURCES.txt
midas_engine.egg-info/dependency_links.txt
midas_engine.egg-info/top_level.txt
midas_engine/Algorithms/BasicFrameWorkAlgorithm.py
midas_engine/Algorithms/MasterAlgorithm.py
midas_engine/Algorithms/__init__.py
midas_engine/Algorithms/config.py
midas_engine/Algorithms/pyrenko.py
midas_engine/Data/Asset.py
midas_engine/Data/__init__.py
midas_engine/Launcher/Engine.py
midas_engine/Launcher/__init__.py
midas_engine/WebSocket/WebsocketHandler.py
midas_engine/WebSocket/__init__.py
midas_engine/misc/RenkoStrat.py
midas_engine/misc/research.py