Metadata-Version: 2.1
Name: midas-engine
Version: 0.0.1
Summary: Trading Engine for Binance
Home-page: https://github.com/eohyungk/midas-engine
Author: Brandon Eo
Author-email: eohyungk@gmail.com
License: UNKNOWN
Platform: UNKNOWN
Classifier: Programming Language :: Python :: 3
Classifier: License :: OSI Approved :: MIT License
Classifier: Operating System :: OS Independent
Requires-Python: >=3.8
